pybrownies/__init__.py
pybrownies/console.py
pybrownies/pprint.py
pybrownies/pprintenv.py
pybrownies/testing.py
pybrownies/whichpy.py
pybrownies/tasks/__init__.py
pybrownies/tasks/__main__.py
pybrownies-0.6.0.dist-info/entry_points.txt
pybrownies-0.6.0.dist-info/LICENSE
pybrownies-0.6.0.dist-info/WHEEL
pybrownies-0.6.0.dist-info/METADATA
pybrownies-0.6.0.dist-info/RECORD
