Metadata-Version: 2.1
Name: pybrownies
Version: 0.6.0
Summary: Little helpers for Python developers
Keywords: helpers
Author-email: Ralf Luetkemeier <foss@rlue.de>
Requires-Python: >=3.9,<4
Classifier: Development Status :: 3 - Alpha
Classifier: Environment :: Console
Classifier: Intended Audience :: Developers
Classifier: License :: OSI Approved :: MIT License
Classifier: Operating System :: MacOS
Classifier: Operating System :: Microsoft :: Windows
Classifier: Operating System :: POSIX :: Linux
Classifier: Programming Language :: Python :: 3
Classifier: Programming Language :: Python :: 3.9
Classifier: Programming Language :: Python :: 3.10
Classifier: Programming Language :: Python :: 3.11
Classifier: Programming Language :: Python :: 3.12
Classifier: Programming Language :: Python :: 3 :: Only
Classifier: Topic :: Software Development
Classifier: Topic :: Software Development :: Build Tools
Classifier: Topic :: Utilities
Requires-Dist: beautifulsoup4 >= 4.11.0
Requires-Dist: invoke >= 2.1.1
Requires-Dist: lxml >= 4.9.0
Requires-Dist: rich >= 12.0.0
Requires-Dist: rich-argparse-plus >= 0.3.0
Requires-Dist: tomli >= 2.0.0; python_version < '3.11'
Requires-Dist: flake8 >=6.0.0 ; extra == "dev"
Requires-Dist: flit >=3.8.0 ; extra == "dev"
Requires-Dist: pylint >=2.16.0 ; extra == "dev"
Requires-Dist: pytest >=7.2.0 ; extra == "dev"
Requires-Dist: pytest-cov >=4.0.0 ; extra == "dev"
Requires-Dist: tox >= 4.4.0 ; extra == "dev"
Requires-Dist: pytest >=7.2.0 ; extra == "tox"
Provides-Extra: dev
Provides-Extra: tox
